reacthass/__init__.py
reacthass/async_reactor.py
reacthass/reactor.py
reacthass-0.1.2.dist-info/LICENSE
reacthass-0.1.2.dist-info/METADATA
reacthass-0.1.2.dist-info/WHEEL
reacthass-0.1.2.dist-info/top_level.txt
reacthass-0.1.2.dist-info/RECORD
