Metadata-Version: 2.1
Name: reacthass
Version: 0.1.2
Summary: Homeassistant API automation helper
Home-page: https://github.com/N4S4/reacthass
Author: Renato Visaggio
License: GPL-3.0 license
License-File: LICENSE
